rizthme/client.py
rizthme/commands/__init__.py
rizthme/commands/kill.py
rizthme/commands/loop.py
rizthme/commands/now.py
rizthme/commands/pause.py
rizthme/commands/play.py
rizthme/commands/resume.py
rizthme/commands/shuffle.py
rizthme/commands/skip.py
rizthme/commands/stop.py
rizthme/commands/unloop.py
rizthme/events/__init__.py
rizthme/events/on_disconnect.py
rizthme/events/on_guild_join.py
rizthme/events/on_guild_remove.py
rizthme/events/on_message.py
rizthme/events/on_ready.py
rizthme/events/on_voice_state_update.py
rizthme/exception.py
rizthme/models/__init__.py
rizthme/models/factory/__init__.py
rizthme/models/factory/audio_factory.py
rizthme/models/mode.py
rizthme/models/music_queue.py
rizthme/models/musics/__init__.py
rizthme/models/musics/audio_item.py
rizthme/models/musics/playable.py
rizthme/models/musics/playlist.py
rizthme/models/musics/simple_music.py
rizthme/models/musics/youtube/__init__.py
rizthme/models/musics/youtube/yt_music.py
rizthme/models/musics/youtube/yt_playlist.py
rizthme/models/threads/__init__.py
rizthme/models/threads/music_queue_adder.py
rizthme/models/threads/player.py
rizthme/models/threads/playlist_queue_adder.py
rizthme/setting/__init__.py
rizthme/setting/config.py
rizthme-2.3.3.dist-info/LICENSE
rizthme-2.3.3.dist-info/METADATA
rizthme-2.3.3.dist-info/WHEEL
rizthme-2.3.3.dist-info/RECORD
