Metadata-Version: 2.1
Name: rizthme
Version: 2.3.3
Summary: Discord Bot
Author: ladettanguy
Author-email: sti2dlab.ladettanguy@gmail.com
Requires-Python: >=3.10,<4.0
Classifier: Programming Language :: Python :: 3
Classifier: Programming Language :: Python :: 3.10
Classifier: Programming Language :: Python :: 3.11
Requires-Dist: discord (>=2.2.2,<3.0.0)
Requires-Dist: ffmpeg (>=1.4,<2.0)
Requires-Dist: multipledispatch (>=0.6.0,<0.7.0)
Requires-Dist: pynacl (>=1.5.0,<2.0.0)
Requires-Dist: pytube (>=12.1.3,<13.0.0)
Requires-Dist: tmktthreader (>=1.0.1,<2.0.0)
